howso/__main__.py
howso/client/__init__.py
howso/client/api.py
howso/client/base.py
howso/client/cache.py
howso/client/client.py
howso/client/configuration.py
howso/client/exceptions.py
howso/client/feature_flags.py
howso/client/protocols.py
howso/client/typing.py
howso/client/pandas/__init__.py
howso/client/pandas/client.py
howso/client/schemas/__init__.py
howso/client/schemas/aggregate_reaction.py
howso/client/schemas/base.py
howso/client/schemas/group_reaction.py
howso/client/schemas/project.py
howso/client/schemas/reaction.py
howso/client/schemas/session.py
howso/client/schemas/trainee.py
howso/client/schemas/version.py
howso/direct/__init__.py
howso/direct/_utilities.py
howso/direct/client.py
howso/direct/schemas/__init__.py
howso/direct/schemas/trainee.py
howso/engine/__init__.py
howso/engine/client.py
howso/engine/project.py
howso/engine/session.py
howso/engine/trainee.py
howso/howso-engine/howso.caml
howso/howso-engine/version.json
howso/howso-engine/migrations/migrations.caml
howso/scikit/__init__.py
howso/scikit/scikit.py
howso/utilities/__init__.py
howso/utilities/features.py
howso/utilities/installation_verification.py
howso/utilities/internals.py
howso/utilities/json_wrapper.py
howso/utilities/locale.py
howso/utilities/monitors.py
howso/utilities/posix.py
howso/utilities/random.py
howso/utilities/reaction.py
howso/utilities/testing.py
howso/utilities/tokenizing.py
howso/utilities/utilities.py
howso/utilities/feature_attributes/__init__.py
howso/utilities/feature_attributes/abstract_data.py
howso/utilities/feature_attributes/base.py
howso/utilities/feature_attributes/infer_feature_attributes.py
howso/utilities/feature_attributes/pandas.py
howso/utilities/feature_attributes/protocols.py
howso/utilities/feature_attributes/relational.py
howso/utilities/feature_attributes/time_series.py
howso_engine-54.2.0.dist-info/licenses/LICENSE-3RD-PARTY.txt
howso_engine-54.2.0.dist-info/licenses/LICENSE.txt
howso_engine-54.2.0.dist-info/METADATA
howso_engine-54.2.0.dist-info/WHEEL
howso_engine-54.2.0.dist-info/entry_points.txt
howso_engine-54.2.0.dist-info/top_level.txt
howso_engine-54.2.0.dist-info/RECORD
