Metadata-Version: 2.4
Name: howso-engine
Version: 54.2.0
Summary: The Howso Engine™ is a natively and fully explainable ML engine, serving as an alternative to black box AI neural networks.
Author: Howso Incorporated
Author-email: support@howso.com
License: GNU AFFERO GENERAL PUBLIC LICENSE
Project-URL: homepage, https://howso.com
Project-URL: documentation, https://docs.howso.com/
Project-URL: repository, https://github.com/howsoai/howso-engine-py
Keywords: machine,learning,artificial,intelligence
Classifier: Development Status :: 5 - Production/Stable
Classifier: Intended Audience :: Science/Research
Classifier: Topic :: Scientific/Engineering :: Artificial Intelligence
Classifier: License :: OSI Approved :: GNU Affero General Public License v3
Classifier: Programming Language :: Python :: 3
Classifier: Programming Language :: Python :: 3.10
Classifier: Programming Language :: Python :: 3.11
Classifier: Programming Language :: Python :: 3.12
Classifier: Programming Language :: Python :: 3.13
Classifier: Operating System :: MacOS
Classifier: Operating System :: MacOS :: MacOS X
Classifier: Operating System :: Microsoft :: Windows
Classifier: Operating System :: Microsoft :: Windows :: Windows 10
Classifier: Operating System :: Microsoft :: Windows :: Windows 11
Classifier: Operating System :: POSIX :: Linux
Requires-Python: >=3.10
License-File: LICENSE-3RD-PARTY.txt
License-File: LICENSE.txt
Requires-Dist: certifi
Requires-Dist: cryptography>=2.9.2
Requires-Dist: deprecation~=2.0
Requires-Dist: Faker>=4.1.1
Requires-Dist: humanize>=4.0.0
Requires-Dist: mmh3
Requires-Dist: numpy
Requires-Dist: pandas<3.0
Requires-Dist: psutil
Requires-Dist: pyjwt~=2.0
Requires-Dist: pyyaml~=6.0
Requires-Dist: requests<3.0,>=2.32.4
Requires-Dist: rich>=12.5.1
Requires-Dist: sacremoses
Requires-Dist: semantic-version~=2.0
Requires-Dist: typing-extensions~=4.9
Requires-Dist: urllib3>=2.6.3
Requires-Dist: amalgam-lang==25.3.0
Provides-Extra: dev
Requires-Dist: dill~=0.0; extra == "dev"
Requires-Dist: flake8-docstrings; extra == "dev"
Requires-Dist: flake8-import-order; extra == "dev"
Requires-Dist: flake8~=3.0; extra == "dev"
Requires-Dist: mongomock; extra == "dev"
Requires-Dist: pip-tools; extra == "dev"
Requires-Dist: pipdeptree; extra == "dev"
Requires-Dist: pycodestyle; extra == "dev"
Requires-Dist: pylint; extra == "dev"
Requires-Dist: pytest<8.0; extra == "dev"
Requires-Dist: pytest-cov; extra == "dev"
Requires-Dist: pytest-xdist; extra == "dev"
Requires-Dist: pytest-mock<1.14.0,~=1.0; extra == "dev"
Provides-Extra: no-telemetry
Requires-Dist: howso-engine-no-telemetry; extra == "no-telemetry"
Provides-Extra: scikit
Requires-Dist: scikit-learn~=1.5; extra == "scikit"
Dynamic: license-file
